[
  {
    "name": "UNFPA yellow",
    "background": "#ffd558",
    "headline": "#5d6260",
    "xrefBackground": "#fc3",
    "quote": "#5d6260",
    "highlightColor": "#cc0033",
    "xref": "#7e6e5b",
    "promo": "#808080",
    "headlineFont": "unfpabold",
    "creditFont": "eureka-bold",
    "promoFont": "unfpabold",
    "xrefFont": "unfpabold",
    "images": {
      "logoSrc": "logoSrc",
      "logoAltSrc": "logoAltSrc",
      "logoBW": "logoBW",
      "logoWhite": "logoWhite",      
      "headshotSrc": "headshotSrc",
      "bookmark": "bookmark",
      "graphSrc": "graphSrc",
      "graphWideSrc": "graphWideSrc",
      "promoSrc": "promoSrc",
      "weekendSrc": "weekendSrc",
      "illustrationSrc": "illustrationSrc",
      "pullquoteSrc": "pullquoteSrc",
      "GlobalgoalsSrc": "GlobalgoalsSrc",
      "GlobalgoalsSrcWhite": "GlobalgoalsSrcWhite",
      "nikkeiAsianReviewLogoWideSrc": "nikkeiAsianReviewLogoWideSrc",
      "SWOPfr": "SWOPfr",
      "SWOPwh": "SWOPwh",
      "SWOPfrWh": "SWOPfrWh",
      "SWOPes":	"SWOPes",
      "SWOPesWh": "SWOPesWh",
      "WPD": "WPD",
      "WPDwh":   "WPDwh",
      "WPDfr": "WPDfr",
      "WPDfrWh": "WPDfrWh",
      "WPDes": "WPDes",
      "WPDesWh": "WPDesWh",
      "MN": "MN",
      "MNwh": "MNwh",
      "MNverb": "MNverb",
      "MNverbWh": "MNverbWh",
      "MNar": "MNar",
      "MNch": "MNch",
      "MNfr": "MNfr",
      "MNes": "MNes"
    }
  },  
  {
    "name": "Light blue",
    "background": "#fc3",
    "headline": "#7e6e5b",
    "xrefBackground": "#8fc3e9",
    "quote": "#7e6e5b",
    "highlightColor": "#cc0033",
    "xref": "#ffffff",
    "headlineFont": "unfpabold",
    "creditFont": "eureka-bold",
    "promoFont": "unfpabold",
    "xrefFont": "unfpabold",
    "images": {
      "logoSrc": "logoSrc",
      "logoAltSrc": "logoAltSrc",
      "logoBW": "logoBW",
      "logoWhite": "logoWhite",      
      "headshotSrc": "headshotSrc",
      "bookmark": "bookmark",
      "graphSrc": "graphSrc",
      "graphWideSrc": "graphWideSrc",
      "promoSrc": "promoSrc",
      "weekendSrc": "weekendSrc",
      "illustrationSrc": "illustrationSrc",
      "pullquoteSrc": "pullquoteSrc",
      "GlobalgoalsSrc": "GlobalgoalsSrc",
      "GlobalgoalsSrcWhite": "GlobalgoalsSrcWhite",
      "nikkeiAsianReviewLogoWideSrc": "nikkeiAsianReviewLogoWideSrc",
      "SWOPfr": "SWOPfr",
      "SWOPwh": "SWOPwh",
      "SWOPfrWh": "SWOPfrWh",
      "SWOPes":	"SWOPes",
      "SWOPesWh": "SWOPesWh",
      "WPD": "WPD",
      "WPDwh":   "WPDwh",
      "WPDfr": "WPDfr",
      "WPDfrWh": "WPDfrWh",
      "WPDes": "WPDes",
      "WPDesWh": "WPDesWh",
      "MN": "MN",
      "MNwh": "MNwh",
      "MNverb": "MNverb",
      "MNverbWh": "MNverbWh",
      "MNar": "MNar",
      "MNch": "MNch",
      "MNfr": "MNfr",
      "MNes": "MNes"
    }
  },
  {
    "name": "Dark blue",
    "background": "#f7f5ef",
    "headline": "#333333",
    "xrefBackground": "#234c84",
    "quote": "#333333",
    "highlightColor": "#cc0033",
    "xref": "#ffffff",
    "headlineFont": "unfpabold",
    "creditFont": "eureka-bold",
    "promoFont": "unfpabold",
    "xrefFont": "unfpabold",
    "images": {
      "logoSrc": "logoSrc",
      "logoAltSrc": "logoAltSrc",
      "logoBW": "logoBW",
      "logoWhite": "logoWhite",
      "headshotSrc": "headshotSrc",
      "bookmark": "bookmark",
      "graphSrc": "graphSrc",
      "graphWideSrc": "graphWideSrc",
      "promoSrc": "promoSrc",
      "weekendSrc": "weekendSrc",
      "illustrationSrc": "illustrationSrc",
      "pullquoteSrc": "pullquoteSrc",
      "GlobalgoalsSrc": "GlobalgoalsSrc",
      "GlobalgoalsSrcWhite": "GlobalgoalsSrcWhite",
      "nikkeiAsianReviewLogoWideSrc": "nikkeiAsianReviewLogoWideSrc",
      "SWOPfr": "SWOPfr",
      "SWOPwh": "SWOPwh",
      "SWOPfrWh": "SWOPfrWh",
      "SWOPes":	"SWOPes",
      "SWOPesWh": "SWOPesWh",
      "WPD": "WPD",
      "WPDwh":   "WPDwh",
      "WPDfr": "WPDfr",
      "WPDfrWh": "WPDfrWh",
      "WPDes": "WPDes",
      "WPDesWh": "WPDesWh",
      "MN": "MN",
      "MNwh": "MNwh",
      "MNverb": "MNverb",
      "MNverbWh": "MNverbWh",
      "MNar": "MNar",
      "MNch": "MNch",
      "MNfr": "MNfr",
      "MNes": "MNes"
    }
  },
  {
    "name": "Dark",
    "background": "#000000",
    "headline": "#ffffff",
    "xrefBackground": "#41474E",
    "quote": "#ffffff",
    "highlightColor": "#cc0033",
    "xref": "#dbe0e6",
    "headlineFont": "unfpabold",
    "creditFont": "eureka-bold",
    "promoFont": "unfpabold",
    "xrefFont": "unfpabold",
    "images": {
      "logoSrc": "logoWhite",
      "logoAltSrc": "logoAltSrc",
      "logoBW": "logoBW",
      "logoWhite": "logoWhite",
      "headshotSrc": "headshotSrc",
      "bookmark": "bookmark",
      "graphSrc": "graphSrcWhite",
      "graphWideSrc": "graphWideSrcWhite",
      "promoSrc": "promoSrc",
      "weekendSrc": "weekendSrc",
      "illustrationSrc": "illustrationSrc",
      "pullquoteSrc": "pullquoteSrc",
      "GlobalgoalsSrc": "GlobalgoalsSrcWhite",
      "nikkeiAsianReviewLogoWideSrc": "nikkeiAsianReviewLogoWideSrc",
      "SWOPfr": "SWOPfr",
      "SWOPwh": "SWOPwh",
      "SWOPfrWh": "SWOPfrWh",
      "SWOPes":	"SWOPes",
      "SWOPesWh": "SWOPesWh",
      "WPD": "WPD",
      "WPDwh":   "WPDwh",
      "WPDfr": "WPDfr",
      "WPDfrWh": "WPDfrWh",
      "WPDes": "WPDes",
      "WPDesWh": "WPDesWh",
      "MN": "MN",
      "MNwh": "MNwh",
      "MNverb": "MNverb",
      "MNverbWh": "MNverbWh",
      "MNar": "MNar",
      "MNch": "MNch",
      "MNfr": "MNfr",
      "MNes": "MNes"      
    }
  }, 
  {
    "name": "Pink",
    "background": "#f7f5ef",
    "headline": "#333333",
    "xrefBackground": "#e9779c",
    "quote": "#333333",
    "highlightColor": "#cc0033",
    "xref": "#555555",
    "promo": "#333333",
    "headlineFont": "unfpabold",
    "creditFont": "eureka-bold",
    "promoFont": "unfpabold",
    "xrefFont": "unfpabold",
    "images": {
      "logoSrc": "logoAltSrc",
      "logoAltSrc": "logoAltSrc",
      "logoBW": "logoBW",
      "logoWhite": "logoWhite",
      "headshotSrc": "headshotSrc",
      "bookmark": "bookmark",
      "graphSrc": "graphSrc",
      "graphWideSrc": "graphWideSrc",
      "promoSrc": "promoSrc",
      "weekendSrc": "weekendSrc",
      "illustrationSrc": "illustrationSrc",
      "pullquoteSrc": "pullquoteSrc",
      "GlobalgoalsSrc": "GlobalgoalsSrc",
      "GlobalgoalsSrcWhite": "GlobalgoalsSrcWhite",
      "nikkeiAsianReviewLogoWideSrc": "nikkeiAsianReviewLogoWideSrc",
      "SWOPfr": "SWOPfr",
      "SWOPwh": "SWOPwh",
      "SWOPfrWh": "SWOPfrWh",
      "SWOPes":	"SWOPes",
      "SWOPesWh": "SWOPesWh",
      "WPD": "WPD",
      "WPDwh":   "WPDwh",
      "WPDfr": "WPDfr",
      "WPDfrWh": "WPDfrWh",
      "WPDes": "WPDes",
      "WPDesWh": "WPDesWh",
      "MN": "MN",
      "MNwh": "MNwh",
      "MNverb": "MNverb",
      "MNverbWh": "MNverbWh",
      "MNar": "MNar",
      "MNch": "MNch",
      "MNfr": "MNfr",
      "MNes": "MNes"
    }
  },
  {
    "name": "Bright Pink",
    "background": "#666666",
    "headline": "#e9e7d3",
    "xrefBackground": "#e34985",
    "quote": "#e9e7d3",
    "highlightColor": "#cc0033",
    "xref": "#e9e7d3",
    "promo": "#e9e7d3",
    "headlineFont": "unfpabold",
    "creditFont": "eureka-bold",
    "promoFont": "unfpabold",
    "xrefFont": "unfpabold",
    "images": {
      "logoSrc": "logoAltSrc",
      "logoAltSrc": "logoAltSrc",
      "logoBW": "logoBW",
      "logoWhite": "logoWhite",
      "headshotSrc": "headshotSrc",
      "bookmark": "bookmark",
      "graphSrc": "graphSrcWhite",
      "graphWideSrc": "graphWideSrcWhite",
      "promoSrc": "promoSrc",
      "weekendSrc": "weekendSrc",
      "illustrationSrc": "illustrationSrc",
      "pullquoteSrc": "pullquoteSrc",
      "GlobalgoalsSrc": "GlobalgoalsSrc",
      "GlobalgoalsSrcWhite": "GlobalgoalsSrcWhite",
      "nikkeiAsianReviewLogoWideSrc": "nikkeiAsianReviewLogoWideSrc",
      "SWOPfr": "SWOPfr",
      "SWOPwh": "SWOPwh",
      "SWOPfrWh": "SWOPfrWh",
      "SWOPes":	"SWOPes",
      "SWOPesWh": "SWOPesWh",
      "WPD": "WPD",
      "WPDwh":   "WPDwh",
      "WPDfr": "WPDfr",
      "WPDfrWh": "WPDfrWh",
      "WPDes": "WPDes",
      "WPDesWh": "WPDesWh",
      "MN": "MN",
      "MNwh": "MNwh",
      "MNverb": "MNverb",
      "MNverbWh": "MNverbWh",
      "MNar": "MNar",
      "MNch": "MNch",
      "MNfr": "MNfr",
      "MNes": "MNes"
    }
  },
  {
    "name": "Green",
    "background": "#bdcca5",
    "headline": "#fff",
    "xrefBackground": "#cadb2a",
    "quote": "#fff",
    "highlightColor": "#cc0033",
    "xref": "#3a3a3a",
    "promo": "#fff",
    "headlineFont": "unfpabold",
    "creditFont": "eureka-bold",
    "promoFont": "unfpabold",
    "xrefFont": "unfpabold",
    "images": {
      "logoSrc": "logoSrc",
      "logoAltSrc": "logoAltSrc",
      "logoBW": "logoBW",
      "logoWhite": "logoWhite",
      "headshotSrc": "headshotSrc",
      "bookmark": "bookmark",
      "graphSrc": "graphSrc",
      "graphWideSrc": "graphWideSrc",
      "promoSrc": "promoSrc",
      "weekendSrc": "weekendSrc",
      "illustrationSrc": "illustrationSrc",
      "pullquoteSrc": "pullquoteSrc",
      "GlobalgoalsSrc": "GlobalgoalsSrc",
      "GlobalgoalsSrcWhite": "GlobalgoalsSrcWhite",
      "nikkeiAsianReviewLogoWideSrc": "nikkeiAsianReviewLogoWideSrc",
      "SWOPfr": "SWOPfr",
      "SWOPwh": "SWOPwh",
      "SWOPfrWh": "SWOPfrWh",
      "SWOPes":	"SWOPes",
      "SWOPesWh": "SWOPesWh",
      "WPD": "WPD",
      "WPDwh":   "WPDwh",
      "WPDfr": "WPDfr",
      "WPDfrWh": "WPDfrWh",
      "WPDes": "WPDes",
      "WPDesWh": "WPDesWh",
      "MN": "MN",
      "MNwh": "MNwh",
      "MNverb": "MNverb",
      "MNverbWh": "MNverbWh",
      "MNar": "MNar",
      "MNch": "MNch",
      "MNfr": "MNfr",
      "MNes": "MNes"
    }
  },
    {
    "name": "Canary",
    "background": "#f7f5ef",
    "headline": "#e9e7d3",
    "xrefBackground": "#ebec6d",
    "quote": "#333333",
    "highlightColor": "#cc0033",
    "xref": "#555555",
    "promo": "#e9e7d3",
    "headlineFont": "unfpabold",
    "creditFont": "eureka-bold",
    "promoFont": "unfpabold",
    "xrefFont": "unfpabold",
    "images": {
      "logoSrc": "logoBW",
      "logoAltSrc": "logoAltSrc",
      "logoBW": "logoBW",
      "logoWhite": "logoWhite",
      "headshotSrc": "headshotSrc",
      "bookmark": "bookmark",
      "graphSrc": "graphSrc",
      "graphWideSrc": "graphWideSrc",
      "promoSrc": "promoSrc",
      "weekendSrc": "weekendSrc",
      "illustrationSrc": "illustrationSrc",
      "pullquoteSrc": "pullquoteSrc",
      "GlobalgoalsSrc": "GlobalgoalsSrc",
      "GlobalgoalsSrcWhite": "GlobalgoalsSrcWhite",
      "nikkeiAsianReviewLogoWideSrc": "nikkeiAsianReviewLogoWideSrc",
      "SWOPfr": "SWOPfr",
      "SWOPwh": "SWOPwh",
      "SWOPfrWh": "SWOPfrWh",
      "SWOPes":	"SWOPes",
      "SWOPesWh": "SWOPesWh",
      "WPD": "WPD",
      "WPDwh":   "WPDwh",
      "WPDfr": "WPDfr",
      "WPDfrWh": "WPDfrWh",
      "WPDes": "WPDes",
      "WPDesWh": "WPDesWh",
      "MN": "MN",
      "MNwh": "MNwh",
      "MNverb": "MNverb",
      "MNverbWh": "MNverbWh",
      "MNar": "MNar",
      "MNch": "MNch",
      "MNfr": "MNfr",
      "MNes": "MNes"
    }
  },        
  {
    "name": "Off-white",
    "background": "#ded9c8",
    "headline": "#6c6b68",
    "xrefBackground": "#f7f5ef",
    "quote": "#333333",
    "highlightColor": "#cc0033",
    "xref": "#000000",
    "promo": "#6c6b68",
    "headlineFont": "unfpabold",
    "creditFont": "eureka-bold",
    "promoFont": "unfpabold",
    "xrefFont": "unfpabold",
    "images": {
      "logoSrc": "logoAltSrc",
      "logoAltSrc": "logoAltSrc",
      "logoBW": "logoBW",
      "logoWhite": "logoWhite",
      "headshotSrc": "headshotSrc",
      "bookmark": "bookmark",
      "graphSrc": "graphSrc",
      "graphWideSrc": "graphWideSrc",
      "promoSrc": "promoSrc",
      "weekendSrc": "weekendSrc",
      "illustrationSrc": "illustrationSrc",
      "pullquoteSrc": "pullquoteSrc",
      "GlobalgoalsSrc": "GlobalgoalsSrc",
      "GlobalgoalsSrcWhite": "GlobalgoalsSrcWhite",
      "nikkeiAsianReviewLogoWideSrc": "nikkeiAsianReviewLogoWideSrc",
      "SWOPfr": "SWOPfr",
      "SWOPwh": "SWOPwh",
      "SWOPfrWh": "SWOPfrWh",
      "SWOPes":	"SWOPes",
      "SWOPesWh": "SWOPesWh",
      "WPD": "WPD",
      "WPDwh":   "WPDwh",
      "WPDfr": "WPDfr",
      "WPDfrWh": "WPDfrWh",
      "WPDes": "WPDes",
      "WPDesWh": "WPDesWh",
      "MN": "MN",
      "MNwh": "MNwh",
      "MNverb": "MNverb",
      "MNverbWh": "MNverbWh",
      "MNar": "MNar",
      "MNch": "MNch",
      "MNfr": "MNfr",
      "MNes": "MNes"
    }
  }, 
  {
    "name": "Violet",
    "background": "#8e848d",
    "headline": "#ffffff",
    "xrefBackground": "#a85ea4",
    "quote": "#333333",
    "highlightColor": "#cc0033",
    "xref": "#ffffff",
    "promo": "#6c6b68",
    "headlineFont": "unfpabold",
    "creditFont": "eureka-bold",
    "promoFont": "unfpabold",
    "xrefFont": "unfpabold",
    "images": {
      "logoSrc": "logoSrc",
      "logoAltSrc": "logoAltSrc",
      "logoBW": "logoBW",
      "logoWhite": "logoWhite",
      "headshotSrc": "headshotSrc",
      "bookmark": "bookmark",
      "graphSrc": "graphSrcWhite",
      "graphWideSrc": "graphWideSrcWhite",
      "promoSrc": "promoSrc",
      "weekendSrc": "weekendSrc",
      "illustrationSrc": "illustrationSrc",
      "pullquoteSrc": "pullquoteSrc",
      "GlobalgoalsSrc": "GlobalgoalsSrcWhite",
      "GlobalgoalsSrcWhite": "GlobalgoalsSrcWhite",
      "nikkeiAsianReviewLogoWideSrc": "nikkeiAsianReviewLogoWideSrc",
      "SWOPfr": "SWOPfr",
      "SWOPwh": "SWOPwh",
      "SWOPfrWh": "SWOPfrWh",
      "SWOPes":	"SWOPes",
      "SWOPesWh": "SWOPesWh",
      "WPD": "WPD",
      "WPDwh":   "WPDwh",
      "WPDfr": "WPDfr",
      "WPDfrWh": "WPDfrWh",
      "WPDes": "WPDes",
      "WPDesWh": "WPDesWh",
      "MN": "MN",
      "MNwh": "MNwh",
      "MNverb": "MNverb",
      "MNverbWh": "MNverbWh",
      "MNar": "MNar",
      "MNch": "MNch",
      "MNfr": "MNfr",
      "MNes": "MNes"  
    }
  }
]
